{
  "is_system_setting_read": {
    "title": "Allow viewing system settings",
    "value": true
  },
  "is_system_setting_update": {
    "title": "Allow changing system settings",
    "value": true
  },

  "is_context_read": {
    "title": "Allow viewing contexts",
    "value": true
  },
  "is_context_create": {
    "title": "Allow creating contexts",
    "value": true
  },
  "is_context_update": {
    "title": "Allow changing contexts",
    "value": true
  },
  "is_context_delete": {
    "title": "Allow Delete Contexts",
    "value": true
  },

  "is_role_read": {
    "title": "Allow viewing access policies",
    "value": true
  },
  "is_role_create": {
    "title": "Allow Create access policies",
    "value": true
  },
  "is_role_update": {
    "title": "Allow edit access policies",
    "value": true
  },
  "is_role_delete": {
    "title": "Allow delete access policies",
    "value": true
  },

  "is_user_read": {
    "title": "Allow users to view",
    "value": true
  },
  "is_user_create": {
    "title": "Allow user creation",
    "value": true
  },
  "is_user_update": {
    "title": "Allow editing users",
    "value": true
  },
  "is_user_delete": {
    "title": "Allow deleting users",
    "value": true
  },

  "is_dictionary_read": {
    "title": "Allow to view dictionaries",
    "value": true
  },
  "is_dictionary_create": {
    "title": "Allow to create dictionaries",
    "value": true
  },
  "is_dictionary_update": {
    "title": "Allow editing dictionaries",
    "value": true
  },
  "is_dictionary_delete": {
    "title": "Allow delete dictionaries",
    "value": true
  },

  "is_layout_read": {
    "title": "Allow viewing templates",
    "value": true
  },
  "is_layout_create": {
    "title": "Allow creating templates",
    "value": true
  },
  "is_layout_update": {
    "title": "Allow editing templates",
    "value": true
  },
  "is_layout_delete": {
    "title": "Allow delete templates",
    "value": true
  },

  "is_field_category_read": {
    "title": "Allow viewing field categories",
    "value": true
  },
  "is_field_category_create": {
    "title": "Allow field categories",
    "value": true
  },
  "is_field_category_update": {
    "title": "Allow editing field categories",
    "value": true
  },
  "is_field_category_delete": {
    "title": "Allow deleting field categories",
    "value": true
  },

  "is_field_read": {
    "title": "Allow viewing fields",
    "value": true
  },
  "is_field_create": {
    "title": "Allow create fields",
    "value": true
  },
  "is_field_update": {
    "title": "Allow edit fields",
    "value": true
  },
  "is_field_delete": {
    "title": "Allow delete fields",
    "value": true
  },

  "is_resource_read": {
    "title": "Allow viewing resources",
    "value": true
  },
  "is_resource_create": {
    "title": "Allow create resources",
    "value": true
  },
  "is_resource_update": {
    "title": "Allow editing resources",
    "value": true
  },
  "is_resource_delete": {
    "title": "Allow deleting resources",
    "value": true
  },

  "is_development_access": {
    "title": "Allow access to tab development",
    "value": true
  },

  "is_filesystem_access": {
    "title": "Allow access to the file system",
    "value": true
  },
  "is_filesystem_directory_create": {
    "title": "Allow create directories",
    "value": true
  },
  "is_filesystem_directory_delete": {
    "title": "Allow delete directories",
    "value": true
  },
  "is_filesystem_directory_rename": {
    "title": "Allow renaming directories",
    "value": true
  },
  "is_filesystem_files_rename": {
    "title": "Allow rename files",
    "value": true
  },
  "is_filesystem_files_uploads": {
    "title": "Allow upload files",
    "value": true
  },
  "is_filesystem_files_delete": {
    "title": "Allow deleting files",
    "value": true
  },
  "is_resource_type_read": {
    "title": "Allow viewing resource types",
    "value": true
  }
}
